mcp_server_hubspot/__init__.py
mcp_server_hubspot/faiss_manager.py
mcp_server_hubspot/hubspot_client.py
mcp_server_hubspot/server.py
mcp_server_hubspot/utils.py
mcp_server_hubspot/clients/__init__.py
mcp_server_hubspot/clients/company_client.py
mcp_server_hubspot/clients/contact_client.py
mcp_server_hubspot/clients/conversation_client.py
mcp_server_hubspot/clients/ticket_client.py
mcp_server_hubspot/core/__init__.py
mcp_server_hubspot/core/error_handler.py
mcp_server_hubspot/core/formatters.py
mcp_server_hubspot/core/storage.py
mcp_server_hubspot/handlers/__init__.py
mcp_server_hubspot/handlers/base_handler.py
mcp_server_hubspot/handlers/company_handler.py
mcp_server_hubspot/handlers/contact_handler.py
mcp_server_hubspot/handlers/conversation_handler.py
mcp_server_hubspot/handlers/search_handler.py
mcp_server_hubspot/handlers/ticket_handler.py
mseep_mcp_server_hubspot-0.2.3.dist-info/licenses/LICENSE
mseep_mcp_server_hubspot-0.2.3.dist-info/METADATA
mseep_mcp_server_hubspot-0.2.3.dist-info/WHEEL
mseep_mcp_server_hubspot-0.2.3.dist-info/entry_points.txt
mseep_mcp_server_hubspot-0.2.3.dist-info/top_level.txt
mseep_mcp_server_hubspot-0.2.3.dist-info/RECORD
