Metadata-Version: 2.4
Name: mseep-mcp-server-hubspot
Version: 0.2.3
Summary: A simple Hubspot MCP server
Author-email: mseep <support@skydeck.ai>
Requires-Python: >=3.10
License-File: LICENSE
Requires-Dist: mcp>=1.4.1
Requires-Dist: hubspot-api-client>=11.1.0
Requires-Dist: python-dotenv>=1.0.1
Requires-Dist: faiss-cpu>=1.7.4
Requires-Dist: numpy>=1.24.0
Requires-Dist: sentence-transformers>=2.2.2
Requires-Dist: huggingface-hub==0.14.1
Dynamic: license-file
